[{"confirmed":157692702,"deaths":3391921,"recovered":93709032,"activeCases":60591749,"newCases":0,"newDeaths":0,"newRecovered":0,"date":"5-8"},{"confirmed":158334279,"deaths":3402130,"recovered":94371825,"activeCases":60560324,"newCases":641577,"newDeaths":10209,"newRecovered":662793,"date":"5-9"},{"confirmed":158956114,"deaths":3413255,"recovered":95000511,"activeCases":60542348,"newCases":621835,"newDeaths":11125,"newRecovered":628686,"date":"5-10"},{"confirmed":159694580,"deaths":3427498,"recovered":95751515,"activeCases":60515567,"newCases":738466,"newDeaths":14243,"newRecovered":751004,"date":"5-11"},{"confirmed":160454640,"deaths":3441353,"recovered":96399064,"activeCases":60614223,"newCases":760060,"newDeaths":13855,"newRecovered":647549,"date":"5-12"},{"confirmed":161179904,"deaths":3455038,"recovered":97089181,"activeCases":60635685,"newCases":725264,"newDeaths":13685,"newRecovered":690117,"date":"5-13"},{"confirmed":161897925,"deaths":3468100,"recovered":97754528,"activeCases":60675297,"newCases":718021,"newDeaths":13062,"newRecovered":665347,"date":"5-14"},{"confirmed":162525945,"deaths":3480306,"recovered":98397065,"activeCases":60648574,"newCases":628020,"newDeaths":12206,"newRecovered":642537,"date":"5-15"},{"confirmed":163074549,"deaths":3490362,"recovered":99064469,"activeCases":60519718,"newCases":548604,"newDeaths":10056,"newRecovered":667404,"date":"5-16"},{"confirmed":163614578,"deaths":3501567,"recovered":99808931,"activeCases":60304080,"newCases":540029,"newDeaths":11205,"newRecovered":744462,"date":"5-17"},{"confirmed":164237099,"deaths":3515766,"recovered":100552044,"activeCases":60169289,"newCases":622521,"newDeaths":14199,"newRecovered":743113,"date":"5-18"},{"confirmed":164908717,"deaths":3529333,"recovered":101250071,"activeCases":60129313,"newCases":671618,"newDeaths":13567,"newRecovered":698027,"date":"5-19"},{"confirmed":165188667,"deaths":3542390,"recovered":101886760,"activeCases":59759517,"newCases":279950,"newDeaths":13057,"newRecovered":636689,"date":"5-20"},{"confirmed":165814687,"deaths":3555399,"recovered":102501548,"activeCases":59757740,"newCases":626020,"newDeaths":13009,"newRecovered":614788,"date":"5-21"},{"confirmed":166392887,"deaths":3566934,"recovered":103118309,"activeCases":59707644,"newCases":578200,"newDeaths":11535,"newRecovered":616761,"date":"5-22"},{"confirmed":166869422,"deaths":3576690,"recovered":103620280,"activeCases":59672452,"newCases":476535,"newDeaths":9756,"newRecovered":501971,"date":"5-23"},{"confirmed":167323965,"deaths":3585742,"recovered":104247872,"activeCases":59490351,"newCases":454543,"newDeaths":9052,"newRecovered":627592,"date":"5-24"},{"confirmed":167856146,"deaths":3598926,"recovered":104824935,"activeCases":59432285,"newCases":532181,"newDeaths":13184,"newRecovered":577063,"date":"5-25"},{"confirmed":168424727,"deaths":3611657,"recovered":105380748,"activeCases":59432322,"newCases":568581,"newDeaths":12731,"newRecovered":555813,"date":"5-26"},{"confirmed":168979456,"deaths":3624703,"recovered":106078106,"activeCases":59276647,"newCases":554729,"newDeaths":13046,"newRecovered":697358,"date":"5-27"},{"confirmed":169479741,"deaths":3636658,"recovered":106633069,"activeCases":59210014,"newCases":500285,"newDeaths":11955,"newRecovered":554963,"date":"5-28"},{"confirmed":169961055,"deaths":3647409,"recovered":107140669,"activeCases":59172977,"newCases":481314,"newDeaths":10751,"newRecovered":507600,"date":"5-29"},{"confirmed":170352480,"deaths":3655528,"recovered":107630598,"activeCases":59066354,"newCases":391425,"newDeaths":8119,"newRecovered":489929,"date":"5-30"},{"confirmed":170731385,"deaths":3664237,"recovered":108159767,"activeCases":58907381,"newCases":378905,"newDeaths":8709,"newRecovered":529169,"date":"5-31"},{"confirmed":171195110,"deaths":3679574,"recovered":108743650,"activeCases":58771886,"newCases":463725,"newDeaths":15337,"newRecovered":583883,"date":"6-1"},{"confirmed":171680813,"deaths":3691386,"recovered":109272024,"activeCases":58717403,"newCases":485703,"newDeaths":11812,"newRecovered":528374,"date":"6-2"},{"confirmed":172170024,"deaths":3701306,"recovered":109701214,"activeCases":58767504,"newCases":489211,"newDeaths":9920,"newRecovered":429190,"date":"6-3"},{"confirmed":172589829,"deaths":3712269,"recovered":110226716,"activeCases":58650844,"newCases":419805,"newDeaths":10963,"newRecovered":525502,"date":"6-4"},{"confirmed":172988098,"deaths":3721429,"recovered":110704846,"activeCases":58561823,"newCases":398269,"newDeaths":9160,"newRecovered":478130,"date":"6-5"},{"confirmed":173310789,"deaths":3728499,"recovered":111146372,"activeCases":58435918,"newCases":322691,"newDeaths":7070,"newRecovered":441526,"date":"6-6"},{"confirmed":173632094,"deaths":3736573,"recovered":111568369,"activeCases":58327152,"newCases":321305,"newDeaths":8074,"newRecovered":421997,"date":"6-7"},{"confirmed":173998912,"deaths":3746949,"recovered":111983105,"activeCases":58268858,"newCases":366818,"newDeaths":10376,"newRecovered":414736,"date":"6-8"},{"confirmed":174418403,"deaths":3757400,"recovered":112435800,"activeCases":58225203,"newCases":419491,"newDeaths":10451,"newRecovered":452695,"date":"6-9"},{"confirmed":174867907,"deaths":3773403,"recovered":112849489,"activeCases":58245015,"newCases":449504,"newDeaths":16003,"newRecovered":413689,"date":"6-10"},{"confirmed":175289165,"deaths":3785332,"recovered":113225021,"activeCases":58278812,"newCases":421258,"newDeaths":11929,"newRecovered":375532,"date":"6-11"},{"confirmed":175661068,"deaths":3795088,"recovered":113563995,"activeCases":58301985,"newCases":371903,"newDeaths":9756,"newRecovered":338974,"date":"6-12"},{"confirmed":175963984,"deaths":3804235,"recovered":113993656,"activeCases":58166093,"newCases":302916,"newDeaths":9147,"newRecovered":429661,"date":"6-13"},{"confirmed":176272503,"deaths":3812116,"recovered":114340430,"activeCases":58119957,"newCases":308519,"newDeaths":7881,"newRecovered":346774,"date":"6-14"},{"confirmed":176643833,"deaths":3822698,"recovered":114800575,"activeCases":58020560,"newCases":371330,"newDeaths":10582,"newRecovered":460145,"date":"6-15"},{"confirmed":177040182,"deaths":3832997,"recovered":115149802,"activeCases":58057383,"newCases":396349,"newDeaths":10299,"newRecovered":349227,"date":"6-16"}]