[{"confirmed":151403270,"deaths":3285730,"recovered":88236951,"activeCases":59880589,"newCases":0,"newDeaths":0,"newRecovered":0,"date":"4-30"},{"confirmed":152200029,"deaths":3299007,"recovered":88919401,"activeCases":59981621,"newCases":796759,"newDeaths":13277,"newRecovered":682450,"date":"5-1"},{"confirmed":152874414,"deaths":3309041,"recovered":89612415,"activeCases":59952958,"newCases":674385,"newDeaths":10034,"newRecovered":693014,"date":"5-2"},{"confirmed":153555936,"deaths":3320840,"recovered":90255904,"activeCases":59979192,"newCases":681522,"newDeaths":11799,"newRecovered":643489,"date":"5-3"},{"confirmed":154363355,"deaths":3334917,"recovered":90912804,"activeCases":60115634,"newCases":807419,"newDeaths":14077,"newRecovered":656900,"date":"5-4"},{"confirmed":155204557,"deaths":3349800,"recovered":91626286,"activeCases":60228471,"newCases":841202,"newDeaths":14883,"newRecovered":713482,"date":"5-5"},{"confirmed":156074567,"deaths":3364454,"recovered":92301898,"activeCases":60408215,"newCases":870010,"newDeaths":14654,"newRecovered":675612,"date":"5-6"},{"confirmed":156906973,"deaths":3378850,"recovered":92998027,"activeCases":60530096,"newCases":832406,"newDeaths":14396,"newRecovered":696129,"date":"5-7"},{"confirmed":157692702,"deaths":3392147,"recovered":93709032,"activeCases":60591523,"newCases":785729,"newDeaths":13297,"newRecovered":711005,"date":"5-8"},{"confirmed":158334279,"deaths":3402353,"recovered":94371825,"activeCases":60560101,"newCases":641577,"newDeaths":10206,"newRecovered":662793,"date":"5-9"},{"confirmed":158956114,"deaths":3413477,"recovered":95000511,"activeCases":60542126,"newCases":621835,"newDeaths":11124,"newRecovered":628686,"date":"5-10"},{"confirmed":159694580,"deaths":3427717,"recovered":95751515,"activeCases":60515348,"newCases":738466,"newDeaths":14240,"newRecovered":751004,"date":"5-11"},{"confirmed":160454640,"deaths":3441663,"recovered":96399064,"activeCases":60613913,"newCases":760060,"newDeaths":13946,"newRecovered":647549,"date":"5-12"},{"confirmed":161179904,"deaths":3455399,"recovered":97089181,"activeCases":60635324,"newCases":725264,"newDeaths":13736,"newRecovered":690117,"date":"5-13"},{"confirmed":161897925,"deaths":3468469,"recovered":97754528,"activeCases":60674928,"newCases":718021,"newDeaths":13070,"newRecovered":665347,"date":"5-14"},{"confirmed":162525945,"deaths":3480667,"recovered":98397065,"activeCases":60648213,"newCases":628020,"newDeaths":12198,"newRecovered":642537,"date":"5-15"},{"confirmed":163074549,"deaths":3490721,"recovered":99064469,"activeCases":60519359,"newCases":548604,"newDeaths":10054,"newRecovered":667404,"date":"5-16"},{"confirmed":163614578,"deaths":3501925,"recovered":99808931,"activeCases":60303722,"newCases":540029,"newDeaths":11204,"newRecovered":744462,"date":"5-17"},{"confirmed":164237099,"deaths":3516125,"recovered":100552044,"activeCases":60168930,"newCases":622521,"newDeaths":14200,"newRecovered":743113,"date":"5-18"},{"confirmed":164908717,"deaths":3529684,"recovered":101250071,"activeCases":60128962,"newCases":671618,"newDeaths":13559,"newRecovered":698027,"date":"5-19"},{"confirmed":165188667,"deaths":3542738,"recovered":101886760,"activeCases":59759169,"newCases":279950,"newDeaths":13054,"newRecovered":636689,"date":"5-20"},{"confirmed":165814687,"deaths":3555746,"recovered":102501548,"activeCases":59757393,"newCases":626020,"newDeaths":13008,"newRecovered":614788,"date":"5-21"},{"confirmed":166392887,"deaths":3567276,"recovered":103118309,"activeCases":59707302,"newCases":578200,"newDeaths":11530,"newRecovered":616761,"date":"5-22"},{"confirmed":166869422,"deaths":3577029,"recovered":103620280,"activeCases":59672113,"newCases":476535,"newDeaths":9753,"newRecovered":501971,"date":"5-23"},{"confirmed":167323965,"deaths":3586076,"recovered":104247872,"activeCases":59490017,"newCases":454543,"newDeaths":9047,"newRecovered":627592,"date":"5-24"},{"confirmed":167856146,"deaths":3599256,"recovered":104824935,"activeCases":59431955,"newCases":532181,"newDeaths":13180,"newRecovered":577063,"date":"5-25"},{"confirmed":168424727,"deaths":3611979,"recovered":105380748,"activeCases":59432000,"newCases":568581,"newDeaths":12723,"newRecovered":555813,"date":"5-26"},{"confirmed":168979456,"deaths":3625017,"recovered":106078106,"activeCases":59276333,"newCases":554729,"newDeaths":13038,"newRecovered":697358,"date":"5-27"},{"confirmed":169479741,"deaths":3636986,"recovered":106633069,"activeCases":59209686,"newCases":500285,"newDeaths":11969,"newRecovered":554963,"date":"5-28"},{"confirmed":169961055,"deaths":3647753,"recovered":107140669,"activeCases":59172633,"newCases":481314,"newDeaths":10767,"newRecovered":507600,"date":"5-29"},{"confirmed":170352480,"deaths":3655869,"recovered":107630598,"activeCases":59066013,"newCases":391425,"newDeaths":8116,"newRecovered":489929,"date":"5-30"},{"confirmed":170731385,"deaths":3664577,"recovered":108159767,"activeCases":58907041,"newCases":378905,"newDeaths":8708,"newRecovered":529169,"date":"5-31"},{"confirmed":171195110,"deaths":3679913,"recovered":108743650,"activeCases":58771547,"newCases":463725,"newDeaths":15336,"newRecovered":583883,"date":"6-1"},{"confirmed":171680812,"deaths":3691721,"recovered":109271887,"activeCases":58717204,"newCases":485702,"newDeaths":11808,"newRecovered":528237,"date":"6-2"},{"confirmed":172169929,"deaths":3701630,"recovered":109700897,"activeCases":58767402,"newCases":489117,"newDeaths":9909,"newRecovered":429010,"date":"6-3"},{"confirmed":172589646,"deaths":3712569,"recovered":110226256,"activeCases":58650821,"newCases":419717,"newDeaths":10939,"newRecovered":525359,"date":"6-4"},{"confirmed":172988007,"deaths":3721736,"recovered":110704680,"activeCases":58561591,"newCases":398361,"newDeaths":9167,"newRecovered":478424,"date":"6-5"},{"confirmed":173310648,"deaths":3728885,"recovered":111146013,"activeCases":58435750,"newCases":322641,"newDeaths":7149,"newRecovered":441333,"date":"6-6"},{"confirmed":173631266,"deaths":3736961,"recovered":111567881,"activeCases":58326424,"newCases":320618,"newDeaths":8076,"newRecovered":421868,"date":"6-7"},{"confirmed":173997437,"deaths":3747371,"recovered":111982400,"activeCases":58267666,"newCases":366171,"newDeaths":10410,"newRecovered":414519,"date":"6-8"}]