[{"confirmed":74278168,"deaths":1649282,"recovered":42048017,"activeCases":30580869,"newCases":0,"newDeaths":0,"newRecovered":0,"date":"12-16"},{"confirmed":75014795,"deaths":1662529,"recovered":42420687,"activeCases":30931579,"newCases":736627,"newDeaths":13247,"newRecovered":372670,"date":"12-17"},{"confirmed":75732956,"deaths":1675148,"recovered":42738659,"activeCases":31319149,"newCases":718161,"newDeaths":12619,"newRecovered":317972,"date":"12-18"},{"confirmed":76345417,"deaths":1685749,"recovered":43093742,"activeCases":31565926,"newCases":612461,"newDeaths":10601,"newRecovered":355083,"date":"12-19"},{"confirmed":76880888,"deaths":1693414,"recovered":43367172,"activeCases":31820302,"newCases":535471,"newDeaths":7665,"newRecovered":273430,"date":"12-20"},{"confirmed":77429015,"deaths":1702896,"recovered":43707973,"activeCases":32018146,"newCases":548127,"newDeaths":9482,"newRecovered":340801,"date":"12-21"},{"confirmed":78075852,"deaths":1717153,"recovered":44069220,"activeCases":32289479,"newCases":646837,"newDeaths":14257,"newRecovered":361247,"date":"12-22"},{"confirmed":78770004,"deaths":1730930,"recovered":44393812,"activeCases":32645262,"newCases":694152,"newDeaths":13777,"newRecovered":324592,"date":"12-23"},{"confirmed":79436753,"deaths":1742536,"recovered":44711774,"activeCases":32982443,"newCases":666749,"newDeaths":11606,"newRecovered":317962,"date":"12-24"},{"confirmed":79905724,"deaths":1750816,"recovered":45002559,"activeCases":33152349,"newCases":468971,"newDeaths":8280,"newRecovered":290785,"date":"12-25"},{"confirmed":80416535,"deaths":1757888,"recovered":45410291,"activeCases":33248356,"newCases":510811,"newDeaths":7072,"newRecovered":407732,"date":"12-26"},{"confirmed":80856030,"deaths":1765126,"recovered":45698093,"activeCases":33392811,"newCases":439495,"newDeaths":7238,"newRecovered":287802,"date":"12-27"},{"confirmed":81349247,"deaths":1774686,"recovered":45994203,"activeCases":33580358,"newCases":493217,"newDeaths":9560,"newRecovered":296110,"date":"12-28"},{"confirmed":82008964,"deaths":1789935,"recovered":46348935,"activeCases":33870094,"newCases":659717,"newDeaths":15249,"newRecovered":354732,"date":"12-29"},{"confirmed":82768267,"deaths":1805232,"recovered":46731568,"activeCases":34231467,"newCases":759303,"newDeaths":15297,"newRecovered":382633,"date":"12-30"},{"confirmed":83488443,"deaths":1818336,"recovered":47010049,"activeCases":34660058,"newCases":720176,"newDeaths":13104,"newRecovered":278481,"date":"12-31"},{"confirmed":84025713,"deaths":1827732,"recovered":47289078,"activeCases":34908903,"newCases":537270,"newDeaths":9396,"newRecovered":279029,"date":"1-1"},{"confirmed":84649404,"deaths":1835910,"recovered":47595212,"activeCases":35218282,"newCases":623691,"newDeaths":8178,"newRecovered":306134,"date":"1-2"},{"confirmed":85183607,"deaths":1843211,"recovered":47860306,"activeCases":35480090,"newCases":534203,"newDeaths":7301,"newRecovered":265094,"date":"1-3"},{"confirmed":85734208,"deaths":1853501,"recovered":48148226,"activeCases":35732481,"newCases":550601,"newDeaths":10290,"newRecovered":287920,"date":"1-4"},{"confirmed":86469506,"deaths":1868651,"recovered":48464481,"activeCases":36136374,"newCases":735298,"newDeaths":15150,"newRecovered":316255,"date":"1-5"},{"confirmed":87248858,"deaths":1883667,"recovered":48777336,"activeCases":36587855,"newCases":779352,"newDeaths":15016,"newRecovered":312855,"date":"1-6"},{"confirmed":88105210,"deaths":1898021,"recovered":49098418,"activeCases":37108771,"newCases":856352,"newDeaths":14354,"newRecovered":321082,"date":"1-7"},{"confirmed":88927349,"deaths":1913919,"recovered":49396392,"activeCases":37617038,"newCases":822139,"newDeaths":15898,"newRecovered":297974,"date":"1-8"},{"confirmed":89692138,"deaths":1926638,"recovered":49730327,"activeCases":38035173,"newCases":764789,"newDeaths":12719,"newRecovered":333935,"date":"1-9"},{"confirmed":90283088,"deaths":1934805,"recovered":49997720,"activeCases":38350563,"newCases":590950,"newDeaths":8167,"newRecovered":267393,"date":"1-10"},{"confirmed":90900967,"deaths":1945033,"recovered":50285515,"activeCases":38670419,"newCases":617879,"newDeaths":10228,"newRecovered":287795,"date":"1-11"},{"confirmed":91605067,"deaths":1962129,"recovered":50629426,"activeCases":39013512,"newCases":704100,"newDeaths":17096,"newRecovered":343911,"date":"1-12"},{"confirmed":92355264,"deaths":1978741,"recovered":50994811,"activeCases":39381712,"newCases":750197,"newDeaths":16612,"newRecovered":365385,"date":"1-13"},{"confirmed":93110488,"deaths":1994054,"recovered":51363325,"activeCases":39753109,"newCases":755224,"newDeaths":15313,"newRecovered":368514,"date":"1-14"},{"confirmed":93876206,"deaths":2009092,"recovered":51685853,"activeCases":40181261,"newCases":765718,"newDeaths":15038,"newRecovered":322528,"date":"1-15"},{"confirmed":94495403,"deaths":2022125,"recovered":52005821,"activeCases":40467457,"newCases":619197,"newDeaths":13033,"newRecovered":319968,"date":"1-16"},{"confirmed":95045634,"deaths":2030831,"recovered":52318440,"activeCases":40696363,"newCases":550231,"newDeaths":8706,"newRecovered":312619,"date":"1-17"},{"confirmed":95559647,"deaths":2040107,"recovered":52634885,"activeCases":40884655,"newCases":514013,"newDeaths":9276,"newRecovered":316445,"date":"1-18"},{"confirmed":96167933,"deaths":2056947,"recovered":53035240,"activeCases":41075746,"newCases":608286,"newDeaths":16840,"newRecovered":400355,"date":"1-19"},{"confirmed":96862056,"deaths":2074764,"recovered":53367302,"activeCases":41419990,"newCases":694123,"newDeaths":17817,"newRecovered":332062,"date":"1-20"},{"confirmed":97518881,"deaths":2091509,"recovered":53733212,"activeCases":41694160,"newCases":656825,"newDeaths":16745,"newRecovered":365910,"date":"1-21"},{"confirmed":98177108,"deaths":2107384,"recovered":54115919,"activeCases":41953805,"newCases":658227,"newDeaths":15875,"newRecovered":382707,"date":"1-22"},{"confirmed":98746982,"deaths":2120618,"recovered":54435854,"activeCases":42190510,"newCases":569874,"newDeaths":13234,"newRecovered":319935,"date":"1-23"},{"confirmed":99194405,"deaths":2129409,"recovered":54744470,"activeCases":42320526,"newCases":447423,"newDeaths":8791,"newRecovered":308616,"date":"1-24"}]